aiocrystal/__init__.py
aiocrystal/webhook.py
aiocrystal/utils/__init__.py
aiocrystal/utils/exceptions.py
aiocrystal/utils/handler.py
aiocrystal/utils/types.py
aiocrystal/v3/async_crystal.py
aiocrystal/v3/models.py
aiocrystal-0.1.1.dist-info/METADATA
aiocrystal-0.1.1.dist-info/WHEEL
aiocrystal-0.1.1.dist-info/top_level.txt
aiocrystal-0.1.1.dist-info/RECORD
