Metadata-Version: 2.2
Name: aiocrystal
Version: 0.1.1
Summary: crystlpay easy interaction
Requires-Python: >=3.13
Requires-Dist: aiohttp>=3.11.13
Requires-Dist: fastapi[standard,standart]>=0.115.11
Requires-Dist: flask>=3.1.0
Requires-Dist: pydantic>=2.10.6
Requires-Dist: requests>=2.32.3
